graph_entity/__init__.py
graph_runner/__init__.py
graph_runner-0.0.1.dist-info/METADATA
graph_runner-0.0.1.dist-info/RECORD
graph_runner-0.0.1.dist-info/WHEEL
graph_runner-0.0.1.dist-info/top_level.txt
